Workbook
Name aporte: Planilha1!$E$20
Name patrimonio: Planilha1!$E$23
Name qtd_anos: Planilha1!$E$21
Name rendimentoo_carteira: Planilha1!$E$14
Name taxa_mensal: Planilha1!$E$22

Sheet Planilha1
B10: CONFIGURAÇÕES
B13: Salário | E13: 5000
B14: Rendimento Carteira | E14: 0.012
B15: Sugestão de Investimento | E15: =E13*30% -> 1500
B17: INVESTIMENTO MENSAL
B20: Quanto investir por mês ? | E20: 350
B21: Por Quantos Anos ? | E21: 3
B22: Taxa de Rendimento mensal ? | E22: 0.0105
B23: Patrimônio acumulado ? | E23: =FV(taxa_mensal,qtd_anos*12,aporte*-1) -> 15216.326
B24: Dividendos Mensais ? | E24: =patrimonio*rendimentoo_carteira -> 182.59591
B27: CENÁRIOS | E27: Dividendos
A30: 2 | B30: Valor em 2 anos | D30: =FV($E$22,A30*12,$E$20*-1) -> 9496.8934 | E30: =D30*$E$14 -> 113.96272
A31: 5 | B31: Valor em 5 anos | D31: =FV($E$22,A31*12,$E$20*-1) -> 29048.454 | E31: =D31*$E$14 -> 348.58145
A32: 10 | B32: Valor em 10 anos | D32: =FV($E$22,A32*12,$E$20*-1) -> 83411.29 | E32: =D32*$E$14 -> 1000.9355
A33: 20 | B33: Valor em 20 anos | D33: =FV($E$22,A33*12,$E$20*-1) -> 375545.88 | E33: =D33*$E$14 -> 4506.5505
A34: 30 | B34: Valor em 30 anos | D34: =FV($E$22,A34*12,$E$20*-1) -> 1398700.1 | E34: =D34*$E$14 -> 16784.402
B37: Perfil | D37: Moderado
B38: Valor a ser investido | D38: =aporte -> 350
B40: Tipo de FII | D40: Percentual Sugerido | E40: Valores
B41: Papel | D41: =VLOOKUP($D$37&"."&B41,Planilha2!$A$1:$D$20,4,FALSE) -> 0.32 | E41: =D41*$D$38 -> 112
B42: Tijolo | D42: =VLOOKUP($D$37&"."&B42,Planilha2!$A$1:$D$20,4,FALSE) -> 0.3 | E42: =D42*$D$38 -> 105
B43: Híbridos | D43: =VLOOKUP($D$37&"."&B43,Planilha2!$A$1:$D$20,4,FALSE) -> 0.08 | E43: =D43*$D$38 -> 28
B44: FOFs | D44: =VLOOKUP($D$37&"."&B44,Planilha2!$A$1:$D$20,4,FALSE) -> 0.1 | E44: =D44*$D$38 -> 35
B45: Desenvolvimento | D45: =VLOOKUP($D$37&"."&B45,Planilha2!$A$1:$D$20,4,FALSE) -> 0.1 | E45: =D45*$D$38 -> 35
B46: Hotelarias | D46: =VLOOKUP($D$37&"."&B46,Planilha2!$A$1:$D$20,4,FALSE) -> 0.1 | E46: =D46*$D$38 -> 35
E47: =SUM(E41:E46) -> 350

Sheet Planilha2
I1: %
A2: Chave | B2: PERFIL | C2: Tipo de FII | D2: % | H2: Moderado.Tijolo | I2: =VLOOKUP(H2,$A:$D,4,FALSE) -> 0.3
A3: =B3&"."&C3 -> Conservador.Papel | B3: Conservador | C3: Papel | D3: 0.3
A4: =B4&"."&C4 -> Conservador.Tijolo | B4: Conservador | C4: Tijolo | D4: 0.5
A5: =B5&"."&C5 -> Conservador.Híbridos | B5: Conservador | C5: Híbridos | D5: 0.1
A6: =B6&"."&C6 -> Conservador.FOFs | B6: Conservador | C6: FOFs | D6: 0.1
A7: =B7&"."&C7 -> Conservador.Desenvolvimento | B7: Conservador | C7: Desenvolvimento | D7: 0
A8: =B8&"."&C8 -> Conservador.Hotelarias | B8: Conservador | C8: Hotelarias | D8: 0
A9: =B9&"."&C9 -> Moderado.Papel | B9: Moderado | C9: Papel | D9: 0.32
A10: =B10&"."&C10 -> Moderado.Tijolo | B10: Moderado | C10: Tijolo | D10: 0.3
A11: =B11&"."&C11 -> Moderado.Híbridos | B11: Moderado | C11: Híbridos | D11: 0.08
A12: =B12&"."&C12 -> Moderado.FOFs | B12: Moderado | C12: FOFs | D12: 0.1
A13: =B13&"."&C13 -> Moderado.Desenvolvimento | B13: Moderado | C13: Desenvolvimento | D13: 0.1
A14: =B14&"."&C14 -> Moderado.Hotelarias | B14: Moderado | C14: Hotelarias | D14: 0.1
... A20: =B20&"."&C20 -> Agressivo.Hotelarias | B20: Agressivo | C20: Hotelarias | D20: 0.1
